dataflow/__init__.py
dataflow/boot.py
dataflow/main.py
dataflow/module/__init__.py
dataflow/module/chain/__init__.py
dataflow/module/context/__init__.py
dataflow/module/context/ai.py
dataflow/module/context/datasource.py
dataflow/module/context/etcd.py
dataflow/module/context/kafka.py
dataflow/module/context/langfuse.py
dataflow/module/context/metrics.py
dataflow/module/context/milvus.py
dataflow/module/context/pybatisplus.py
dataflow/module/context/redis.py
dataflow/module/context/stream.py
dataflow/module/context/web.py
dataflow/module/llm/__init__.py
dataflow/router/endpoint.py
dataflow/utils/antpath.py
dataflow/utils/config.py
dataflow/utils/file.py
dataflow/utils/jwt.py
dataflow/utils/log.py
dataflow/utils/reflect.py
dataflow/utils/schedule.py
dataflow/utils/sign.py
dataflow/utils/thread.py
dataflow/utils/utils.py
dataflow/utils/dbtools/etcd.py
dataflow/utils/dbtools/milvus.py
dataflow/utils/dbtools/minio.py
dataflow/utils/dbtools/mysql.py
dataflow/utils/dbtools/pybatis.py
dataflow/utils/dbtools/pydbc.py
dataflow/utils/dbtools/redis.py
dataflow/utils/llm/vector.py
dataflow/utils/mq/kafka.py
dataflow/utils/mq/rocketmq.py
dataflow/utils/trace/langfuse.py
dataflow/utils/web/asgi.py
gohutool_dataflow-1.0.2b5.dist-info/licenses/LICENSE
gohutool_dataflow-1.0.2b5.dist-info/METADATA
gohutool_dataflow-1.0.2b5.dist-info/WHEEL
gohutool_dataflow-1.0.2b5.dist-info/top_level.txt
gohutool_dataflow-1.0.2b5.dist-info/RECORD
